pyefs/__init__.py
pyefs/app.py
pyefs-0.0.1.dist-info/LICENSE
pyefs-0.0.1.dist-info/METADATA
pyefs-0.0.1.dist-info/WHEEL
pyefs-0.0.1.dist-info/top_level.txt
pyefs-0.0.1.dist-info/RECORD
