Metadata-Version: 2.1
Name: pyefs
Version: 0.0.1
Summary: A Python module for encrypting and decrypting files using the Fernet encryption algorithm.
Author-email: joumaico <joumaico@gmx.com>
License: MIT License
Project-URL: Homepage, https://github.com/joumaico/pyefs
Classifier: License :: OSI Approved :: MIT License
Classifier: Programming Language :: Python
Classifier: Programming Language :: Python :: 3
Requires-Python: >=3.10
License-File: LICENSE
Requires-Dist: cryptography (>=40.0.1)
